LICENSE.txt
README.md
setup.cfg
setup.py
uthibs/__init__.py
uthibs/dash_functions.py
uthibs/database_test.py
uthibs/disk_interaction.py
uthibs/general.py
uthibs/geometry.py
uthibs/helper.py
uthibs/ml.py
uthibs/ml_viz.py
uthibs/pg_connection.py
uthibs/secundary.py
uthibs/serie_gestion.py
uthibs/slack.py
uthibs/time_format.py
uthibs/ts_analysis.py
uthibs.egg-info/PKG-INFO
uthibs.egg-info/SOURCES.txt
uthibs.egg-info/dependency_links.txt
uthibs.egg-info/requires.txt
uthibs.egg-info/top_level.txt