Metadata-Version: 2.1
Name: uthibs
Version: 0.0.5
Summary: Re-usable functions from my different projects
Home-page: https://github.com/ThibaudLamothe/uthibs
Author: Thibaud Lamothe
Author-email: hello@etomal.com
License: MIT
Download-URL: https://github.com/ThibaudLamothe/uthibs/archive/refs/tags/v.0.0.1.tar.gz
Keywords: FUNCTIONS,UTILS,GENERIC
Platform: UNKNOWN
Classifier: Development Status :: 3 - Alpha
Classifier: Intended Audience :: Developers
Classifier: Topic :: Software Development :: Build Tools
Classifier: License :: OSI Approved :: MIT License
Classifier: Programming Language :: Python :: 3.7
License-File: LICENSE.txt
